[
{"title": "P/L", "value": "10,02"},
{"title": "EV/EBITDA", "value": "-"},
{"title": "P/VP", "value": "1,20"},
{"title": "EV/EBIT", "value": "5,81"},
{"title": "P/EBITDA", "value": "-"},
{"title": "P/EBIT", "value": "9,54"},
{"title": "VPA", "value": "10,95"},
{"title": "P/Ativo", "value": "0,76"},
{"title": "LPA", "value": "1,31"},
{"title": "P/SR", "value": "2,79"},
{"title": "P/Cap. Giro", "value": "2,52"},
{"title": "P/Ativo Circ. Liq.", "value": "-1,30"},
{"title": "D\u00edv. l\u00edquida/PL", "value": "-0,47"},
{"title": "D\u00edv. l\u00edquida/EBITDA", "value": "-"},
{"title": "D\u00edv. l\u00edquida/EBIT", "value": "-3,72"},
{"title": "PL/Ativos", "value": "0,63"},
{"title": "Passivo/Ativos", "value": "0,37"},
{"title": "Liq. corrente", "value": "3,55"},
{"title": "M. Bruta", "value": "29,88%"},
{"title": "M. EBITDA", "value": "-%"},
{"title": "M. EBIT", "value": "29,22%"},
{"title": "M. L\u00edquida", "value": "27,79%"},
{"title": "ROE", "value": "11,98%"},
{"title": "ROA", "value": "7,56%"},
{"title": "ROIC", "value": "8,64%"},
{"title": "Giro ativos", "value": "0,27"},
{"title": "CAGR Receitas 5 anos", "value": "17,18%"},
{"title": "CAGR Lucros 5 anos", "value": "2,03%"}
]