[
{"title": "P/L", "value": "0,56"},
{"title": "EV/EBITDA", "value": "-"},
{"title": "P/VP", "value": "1,50"},
{"title": "EV/EBIT", "value": "27,39"},
{"title": "P/EBITDA", "value": "-"},
{"title": "P/EBIT", "value": "19,59"},
{"title": "VPA", "value": "106,53"},
{"title": "P/Ativo", "value": "0,34"},
{"title": "LPA", "value": "286,47"},
{"title": "P/SR", "value": "0,30"},
{"title": "P/Cap. Giro", "value": "1,67"},
{"title": "P/Ativo Circ. Liq.", "value": "-0,69"},
{"title": "D\u00edv. l\u00edquida/PL", "value": "0,60"},
{"title": "D\u00edv. l\u00edquida/EBITDA", "value": "-"},
{"title": "D\u00edv. l\u00edquida/EBIT", "value": "7,80"},
{"title": "PL/Ativos", "value": "0,23"},
{"title": "Passivo/Ativos", "value": "0,77"},
{"title": "Liq. corrente", "value": "1,68"},
{"title": "M. Bruta", "value": "17,61%"},
{"title": "M. EBITDA", "value": "-%"},
{"title": "M. EBIT", "value": "1,52%"},
{"title": "M. L\u00edquida", "value": "53,40%"},
{"title": "ROE", "value": "268,91%"},
{"title": "ROA", "value": "61,28%"},
{"title": "ROIC", "value": "-47,66%"},
{"title": "Giro ativos", "value": "1,15"},
{"title": "CAGR Receitas 5 anos", "value": "7,39%"},
{"title": "CAGR Lucros 5 anos", "value": "-%"}
]