[
{"title": "P/L", "value": "4,76"},
{"title": "EV/EBITDA", "value": "1,11"},
{"title": "P/VP", "value": "14,52"},
{"title": "EV/EBIT", "value": "1,32"},
{"title": "P/EBITDA", "value": "2,53"},
{"title": "P/EBIT", "value": "3,01"},
{"title": "VPA", "value": "10,05"},
{"title": "P/Ativo", "value": "0,43"},
{"title": "LPA", "value": "30,67"},
{"title": "P/SR", "value": "0,53"},
{"title": "P/Cap. Giro", "value": "-1,65"},
{"title": "P/Ativo Circ. Liq.", "value": "-0,63"},
{"title": "D\u00edv. l\u00edquida/PL", "value": "0,40"},
{"title": "D\u00edv. l\u00edquida/EBITDA", "value": "0,07"},
{"title": "D\u00edv. l\u00edquida/EBIT", "value": "0,08"},
{"title": "PL/Ativos", "value": "0,03"},
{"title": "Passivo/Ativos", "value": "0,97"},
{"title": "Liq. corrente", "value": "0,54"},
{"title": "M. Bruta", "value": "33,69%"},
{"title": "M. EBITDA", "value": "20,74%"},
{"title": "M. EBIT", "value": "17,43%"},
{"title": "M. L\u00edquida", "value": "11,04%"},
{"title": "ROE", "value": "305,14%"},
{"title": "ROA", "value": "9,12%"},
{"title": "ROIC", "value": "232,80%"},
{"title": "Giro ativos", "value": "0,83"},
{"title": "CAGR Receitas 5 anos", "value": "4,32%"},
{"title": "CAGR Lucros 5 anos", "value": "19,67%"}
]